{
  "title_screen": {
    "category": "music",
    "sounds": [
        {
			"name": "terrariamod:music/title_screen",
			"stream": true
		}
    ]
  },
  "day1": {
	"category": "music",
	"sounds": [
		{
			"name": "terrariamod:music/day1",
			"stream": true
		}
	]
  },
  "windy_day": {
	"category": "music",
	"sounds": [
		{
			"name": "terrariamod:music/windy_day",
			"stream": true
		}
	]
  },
  "mushroom": {
	"category": "music",
	"sounds": [
		{
			"name": "terrariamod:music/mushroom",
			"stream": true
		}
	]
  },
  "snow": {
	"category": "music",
	"sounds": [
		{
			"name": "terrariamod:music/snow",
			"stream": true
		}
	]
  },
  "corruption": {
	"category": "music",
	"sounds": [
		{
			"name": "terrariamod:music/corruption",
			"stream": true
		}
	]
  },
  "desert": {
	"category": "music",
	"sounds": [
		{
			"name": "terrariamod:music/desert",
			"stream": true
		}
	]
  },
  "night": {
	"category": "music",
	"sounds": [
		{
			"name": "terrariamod:music/night",
			"stream": true
		}
	]
  },
  "underground": {
	"category": "music",
	"sounds": [
		{
			"name": "terrariamod:music/underground1",
			"stream": true
		}
	]
  },
  "underground_corruption": {
	"category": "music",
	"sounds": [
		{
			"name": "terrariamod:music/underground_corruption",
			"stream": true
		}
	]
  },
  "bloodmoon": {
	"category": "music",
	"sounds": [
		{
			"name": "terrariamod:music/blood_moon",
			"stream": true
		}
	]
  },
  "eclipse": {
	"category": "music",
	"sounds": [
		{
			"name": "terrariamod:music/eclipse",
			"stream": true
		}
	]
  },
  "boss1": {
	"category": "music",
	"sounds": [
		{
			"name": "terrariamod:music/boss1",
			"stream": true
		}
	]
  },
  "boss2": {
	"category": "music",
	"sounds": [
		{
			"name": "terrariamod:music/boss2",
			"stream": true
		}
	]
  },
  "underworld": {
	"category": "music",
	"sounds": [
		{
			"name": "terrariamod:music/underworld",
			"stream": true
		}
	]
  },
  "sc": {
	"category": "music",
	"sounds": [
		{
			"name": "terrariamod:music/sc",
			"stream": true
		}
	]
  },
  "hallow": {
	"category": "music",
	"sounds": [
		{
			"name": "terrariamod:music/hallow",
			"stream": true
		}
	]
  },
  "boss3": {
	"category": "music",
	"sounds": [
		{
			"name": "terrariamod:music/boss3",
			"stream": true
		}
	]
  },
  "crimson": {
	"category": "music",
	"sounds": [
		{
			"name": "terrariamod:music/crimson",
			"stream": true
		}
	]
  },
  "ocean": {
	"category": "music",
	"sounds": [
		{
			"name": "terrariamod:music/ocean",
			"stream": true
		}
	]
  },
  "jungle": {
	"category": "music",
	"sounds": [
		{
			"name": "terrariamod:music/jungle",
			"stream": true
		}
	]
  },
"lunar_event": {
	"category": "music",
	"sounds": [
		{
			"name": "terrariamod:music/lunar_event",
			"stream": true
		}
	]
  },
"moon_lord": {
	"category": "music",
	"sounds": [
		{
			"name": "terrariamod:music/moon_lord",
			"stream": true
		}
	]
  },
"plantera": {
	"category": "music",
	"sounds": [
		{
			"name": "terrariamod:music/plantera",
			"stream": true
		}
	]
  },
"golem": {
	"category": "music",
	"sounds": [
		{
			"name": "terrariamod:music/golem",
			"stream": true
		}
	]
  },
"rain": {
	"category": "music",
	"sounds": [
		{
			"name": "terrariamod:music/rain",
			"stream": true
		}
	]
  },
  "star_fall": {
		"category": "players",
		"subtitle": "terrariamod.star_fall",
		"sounds": [ "terrariamod:star_fall" ]
	},
  "roar_0": {
	"category": "players",
	"subtitle": "terrariamod.roar_0",
	"sounds": [ "terrariamod:roar_0" ]
  },
  "teleport": {
	"category": "players",
	"subtitle": "terrariamod.teleport",
	"sounds": [ "terrariamod:teleport" ]
  },
  "menu_open": {
	"category": "players",
	"subtitle": "terrariamod.menu_open",
	"sounds": [ "terrariamod:menu_open" ]
  },
  "menu_close": {
	"category": "players",
	"subtitle": "terrariamod.menu_close",
	"sounds": [ "terrariamod:menu_close" ]
  },
  "grab": {
	"category": "players",
	"subtitle": "terrariamod.grab",
	"sounds": [ "terrariamod:grab" ]
  },
  "health_crystal": {
	"category": "players",
	"subtitle": "terrariamod.health_crystal",
	"sounds": [ "terrariamod:health_crystal" ]
  },
  "crystal_destroy": {
	"category": "block",
	"subtitle": "terrariamod.crystal_destroy",
	"sounds": [ "terrariamod:crystal_destroy" ]
  },
  "tink0": {
	"category": "block",
	"subtitle": "terrariamod.tink0",
	"sounds": [ "terrariamod:tink0" ]
  },
  "dig0": {
	"category": "block",
	"subtitle": "terrariamod.dig0",
	"sounds": [ "terrariamod:dig0" ]
  },
  "shatter": {
	"category": "sounds",
	"subtitle": "terrariamod.shatter",
	"sounds": [ "terrariamod:shatter" ]
  },
"npc_hit1": {
	"category": "sounds",
	"subtitle": "terrariamod.npc_hit1",
	"sounds": [ "terrariamod:npc_hit1" ]
  },
"npc_hit2": {
	"category": "sounds",
	"subtitle": "terrariamod.npc_hit2",
	"sounds": [ "terrariamod:npc_hit2" ]
  },
"npc_hit13": {
	"category": "sounds",
	"subtitle": "terrariamod.npc_hit13",
	"sounds": [ "terrariamod:npc_hit13" ]
  },
"npc_hit19": {
	"category": "sounds",
	"subtitle": "terrariamod.npc_hit19",
	"sounds": [ "terrariamod:npc_hit19" ]
  },
"npc_killed1": {
	"category": "sounds",
	"subtitle": "terrariamod.npc_killed1",
	"sounds": [ "terrariamod:npc_killed1" ]
  },
"npc_killed2": {
	"category": "sounds",
	"subtitle": "terrariamod.npc_killed2",
	"sounds": [ "terrariamod:npc_killed2" ]
  },
"npc_killed10": {
	"category": "sounds",
	"subtitle": "terrariamod.npc_killed10",
	"sounds": [ "terrariamod:npc_killed10" ]
  },
"npc_killed12": {
	"category": "sounds",
	"subtitle": "terrariamod.npc_killed12",
	"sounds": [ "terrariamod:npc_killed12" ]
  },
"zombie1": {
	"category": "sounds",
	"subtitle": "terrariamod.zombie1",
	"sounds": [ "terrariamod:zombie1" ]
  }
}